{
	"CreationDate": 739629329.905831,
	"UID": "94097E0E-C4AF-4E2A-A6E1-DCD5B1534322",
	"Name": "Mouseles",
	"Triggers": [
		{
			"Application": {
				"BundleIdentifier": "net.sonuscape.mouseless",
				"Name": "Mouseless",
				"NewFile": "/Applications/Mouseless.app"
			},
			"FireType2": "Quit",
			"RepeatTime": 60,
			"Target": "Specific",
			"MacroTriggerType": "Application"
		}
	],
	"ModificationDate": 756848440.408055,
	"Actions": [
		{
			"MacroActionType": "Notification",
			"Title": "Mouseless Closed",
			"SoundName": "",
			"Subtitle": "",
			"Text": "Mouseless Quit. It will open in 5 seconds unless you cancel all Macros with ALT + ESC",
			"ActionUID": 15569331
		},
		{
			"MacroActionType": "Pause",
			"TimeOutAbortsMacro": true,
			"Time": "5",
			"ActionUID": 15569332
		},
		{
			"MacroActionType": "ActivateApplication",
			"ActionUID": 15569333,
			"ReopenWindows": false,
			"AllWindows": false,
			"TimeOutAbortsMacro": true,
			"AlreadyActivatedActionType": "Normal",
			"Application": {
				"BundleIdentifier": "net.sonuscape.mouseless",
				"Name": "Mouseless",
				"NewFile": "/Applications/Mouseless.app"
			}
		}
	]
}