{
	"CreationDate": 744304896.555522,
	"UID": "8A9F0A33-A016-4C5B-9A54-ADA0DCF262D7",
	"Name": "Dropover Cloud Link",
	"Triggers": [],
	"ModificationDate": 744304925.748359,
	"Actions": [
		{
			"MacroActionType": "SetVariableToText",
			"Variable": "localMousePos",
			"Text": "%Calculate%MOUSEX()%, %Calculate%MOUSEY()%",
			"ActionUID": 15521820
		},
		{
			"MacroActionType": "ExecuteMacro",
			"UseParameter": false,
			"MacroUID": "00F588A9-A5BB-48E8-8A8C-9F25658FB66A",
			"TimeOutAbortsMacro": true,
			"Asynchronously": false,
			"ActionUID": 15521821
		},
		{
			"MacroActionType": "MouseMoveAndClick",
			"DragVerticalPosition": "0",
			"ClickCount": 1,
			"Modifiers": 0,
			"Button": 1,
			"Fuzz": 15,
			"Action": "MoveAndClick",
			"DisplayMatches": false,
			"ActionUID": 15521822,
			"DragHorizontalPosition": "0",
			"RestoreMouseLocation": false,
			"RelativeCorner": "TopLeft",
			"VerticalPositionExpression": "0",
			"HorizontalPositionExpression": "0",
			"Relative": "Mouse",
			"MouseDrag": "Hold"
		},
		{
			"MacroActionType": "Pause",
			"TimeOutAbortsMacro": true,
			"Time": ".1",
			"ActionUID": 15521823
		},
		{
			"MacroActionType": "MouseMoveAndClick",
			"DragVerticalPosition": "0",
			"ClickCount": -1,
			"Modifiers": 0,
			"Button": 1,
			"Fuzz": 15,
			"Action": "MoveAndClick",
			"DisplayMatches": false,
			"ActionUID": 15521824,
			"DragHorizontalPosition": "0",
			"RestoreMouseLocation": false,
			"RelativeCorner": "TopLeft",
			"VerticalPositionExpression": "0",
			"HorizontalPositionExpression": "0",
			"Relative": "Window",
			"MouseDrag": "None"
		},
		{
			"MacroActionType": "Pause",
			"TimeOutAbortsMacro": true,
			"Time": ".1",
			"ActionUID": 15521825
		},
		{
			"MacroActionType": "InsertText",
			"Text": "copy dropover",
			"TargetApplication": {},
			"Action": "ByTyping",
			"TargetingType": "Front",
			"ActionUID": 15521826
		},
		{
			"MacroActionType": "SimulateKeystroke",
			"ActionUID": 15521827,
			"ReleaseAll": false,
			"TargetApplication": {},
			"TargetingType": "Front",
			"KeyCode": 36,
			"Modifiers": 0
		},
		{
			"MacroActionType": "Pause",
			"TimeOutAbortsMacro": true,
			"Time": ".1",
			"ActionUID": 15521828
		},
		{
			"MacroActionType": "UseVariable",
			"Action": "SetMouse",
			"Variable": "localMousePos",
			"ActionUID": 15521829
		}
	]
}